<?xml version="1.0" encoding="UTF-8"?>
<modification
    application="Heroes of Newerth"
    appversion="*"
    mmversion="1.0"
    name="Titan UI"
    version="1.1"
    description="TODO"
    author="Wiggy boy"

    weblink=""
    updatecheckurl=""
    updatedownloadurl=""
>
    <!-- Add to Game Overlay Options -->
	<editfile name="ui/fe2/game_options.package">
        <find><![CDATA[title="options_dropdown_overlayselect"
								maxlistheight="6"
								populate="]]></find>
        <insert position="after"><![CDATA[
									AddTemplateListItem('Ncombobox_item', '/ui/titan-game.interface', 'label', 'options_interface_titan');]]></insert>
    </editfile>

    <!-- Add Titan UI Options -->
	<copyfile name="ui/titan_options.package"/>
    <editfile name="ui/mod_options_elements.package">
        <find><![CDATA[<!-- INSERT AFTER THIS -->]]></find>
        <insert position="after"><![CDATA[
    <include file="/ui/titan_options.package"/>]]></insert>
    </editfile>

    <!-- Copy over Titan UI -->
	<copyfile name="ui/base.lua"/>
	<copyfile name="ui/titan-game.interface"/>
	<copyfile name="ui/titan-game.lua"/>
	<copyfile name="ui/titan-minimap.interface"/>
	<copyfile name="ui/titan-minimap.lua"/>
	<copyfile name="ui/titan-minimap.tga"/>

</modification>
